{
    "number_of_introduce_bugs_per_commit": {
        "#content--any23--dependabot[bot]": 0,
        "#content--any23--lewismc": 0,
        "#content--any23--hboutemy": 0,
        "#content--any23--brnnnfx": 0,
        "#content--any23--NcIgor": 0,
        "#content--any23--tjroamer": 0,
        "#content--any23--kamaci": 0,
        "#content--any23--HansBrende": 0,
        "#content--any23--JLLeitschuh": 0,
        "#content--any23--coheigea": 0,
        "#content--any23--panthony": 0,
        "#content--any23--davidcockbill": 0,
        "#content--any23--afs": 0,
        "#content--any23--jgrzebyta": 0,
        "#content--any23--larsgsvensson": 0,
        "#content--any23--JulioCCBUcuenca": 0,
        "#content--any23--frankier": 0,
        "#content--any23--": 0,
        "#content--any23--The-Alchemist": 0,
        "#content--any23--band": 0,
        "#content--any23--ansell": 0,
        "#content--any23--jonathansantilli": 0,
        "#content--any23--nisalanirmana": 0,
        "#content--any23--michelemostarda": 0,
        "#content--any23--Timpy": 0,
        "#content--any23--scor": 0,
        "#content--any23--jdevelop": 0,
        "#content--any23--levkhomich": 0,
        "#content--any23--simonetripodi": 0,
        "#content--any23--olamy": 0,
        "#content--incubator-freemarker--woonsanko": 0.25,
        "#content--incubator-freemarker--szegedi": 0.07142857142857142,
        "#content--incubator-freemarker--ddekany": 0.0046210720887245845,
        "#content--incubator-freemarker--chrisrueger": 0,
        "#content--incubator-freemarker--": 0,
        "#content--incubator-freemarker--powercomstar": 0,
        "#content--incubator-freemarker--theHacker": 0,
        "#content--incubator-freemarker--ILyaCyclone": 0,
        "#content--incubator-freemarker--agriffis": 0,
        "#content--incubator-freemarker--martin-g": 0,
        "#content--incubator-freemarker--TrackerSB": 0,
        "#content--incubator-freemarker--mbooth101": 0,
        "#content--incubator-freemarker--aschi": 0,
        "#content--incubator-freemarker--quaff": 0,
        "#content--incubator-freemarker--woonsan": 0,
        "#content--incubator-freemarker--vocatan": 0,
        "#content--incubator-freemarker--robin850": 0,
        "#content--incubator-freemarker--ajbanck": 0,
        "#content--incubator-freemarker--ninjyni": 0,
        "#content--incubator-freemarker--chaquotay": 0,
        "#content--incubator-freemarker--fvanderwielen": 0,
        "#content--incubator-freemarker--jyjz2008": 0,
        "#content--incubator-freemarker--pitgrap": 0,
        "#content--incubator-freemarker--SimonLammer": 0,
        "#content--incubator-freemarker--pradeepmurugesan": 0,
        "#content--incubator-freemarker--pyxide": 0,
        "#content--incubator-freemarker--jacopoc": 0,
        "#content--incubator-freemarker--ratherblue": 0,
        "#content--incubator-freemarker--nanlei": 0,
        "#content--incubator-freemarker--mkleine": 0,
        "#content--incubator-freemarker--gamerson": 0,
        "#content--manifoldcf--rafaharo": 0.23076923076923078,
        "#content--manifoldcf--maoo": 0.05555555555555555,
        "#content--manifoldcf--": 0.023148148148148147,
        "#content--manifoldcf--sabe1": 0.014705882352941176,
        "#content--manifoldcf--kishorejangid": 0.00847457627118644,
        "#content--manifoldcf--kwrightapache": 0.00477326968973747,
        "#content--manifoldcf--schuch": 0,
        "#content--manifoldcf--OpenPj": 0,
        "#content--manifoldcf--danielshahaf": 0,
        "#content--manifoldcf--tteofili": 0,
        "#content--manifoldcf--gsingers": 0,
        "#content--manifoldcf--rmuir": 0,
        "#content--manifoldcf--markrmiller": 0,
        "#content--ofbiz--dixitdeepak": 0,
        "#content--ofbiz--pythys": 0,
        "#content--ofbiz--JacquesLeRoux": 0,
        "#content--ofbiz--nmalin": 0,
        "#content--ofbiz--mbrohl": 0,
        "#content--ofbiz--jacopoc": 0,
        "#content--ofbiz--shijh": 0,
        "#content--ofbiz--": 0,
        "#content--ofbiz--hansbak": 0,
        "#content--pdfbox--jmaerki": 2.0,
        "#content--pdfbox--jahewson": 0.7165354330708661,
        "#content--pdfbox--jukka": 0.6779661016949152,
        "#content--pdfbox--lehmi": 0.5106679035250464,
        "#content--pdfbox--": 0.4459677419354839,
        "#content--pdfbox--THausherr": 0.1321882001493652,
        "#content--pdfbox--tballison": 0.125
    },
    "bug_introducing_commit_rate": {
        "#content--any23--dependabot[bot]": 0,
        "#content--any23--lewismc": 0,
        "#content--any23--hboutemy": 0,
        "#content--any23--brnnnfx": 0,
        "#content--any23--NcIgor": 0,
        "#content--any23--tjroamer": 0,
        "#content--any23--kamaci": 0,
        "#content--any23--HansBrende": 0,
        "#content--any23--JLLeitschuh": 0,
        "#content--any23--coheigea": 0,
        "#content--any23--panthony": 0,
        "#content--any23--davidcockbill": 0,
        "#content--any23--afs": 0,
        "#content--any23--jgrzebyta": 0,
        "#content--any23--larsgsvensson": 0,
        "#content--any23--JulioCCBUcuenca": 0,
        "#content--any23--frankier": 0,
        "#content--any23--": 0,
        "#content--any23--The-Alchemist": 0,
        "#content--any23--band": 0,
        "#content--any23--ansell": 0,
        "#content--any23--jonathansantilli": 0,
        "#content--any23--nisalanirmana": 0,
        "#content--any23--michelemostarda": 0,
        "#content--any23--Timpy": 0,
        "#content--any23--scor": 0,
        "#content--any23--jdevelop": 0,
        "#content--any23--levkhomich": 0,
        "#content--any23--simonetripodi": 0,
        "#content--any23--olamy": 0,
        "#content--incubator-freemarker--woonsanko": 0.5,
        "#content--incubator-freemarker--szegedi": 0.07142857142857142,
        "#content--incubator-freemarker--ddekany": 0.013401109057301294,
        "#content--incubator-freemarker--chrisrueger": 0,
        "#content--incubator-freemarker--": 0,
        "#content--incubator-freemarker--powercomstar": 0,
        "#content--incubator-freemarker--theHacker": 0,
        "#content--incubator-freemarker--ILyaCyclone": 0,
        "#content--incubator-freemarker--agriffis": 0,
        "#content--incubator-freemarker--martin-g": 0,
        "#content--incubator-freemarker--TrackerSB": 0,
        "#content--incubator-freemarker--mbooth101": 0,
        "#content--incubator-freemarker--aschi": 0,
        "#content--incubator-freemarker--quaff": 0,
        "#content--incubator-freemarker--woonsan": 0,
        "#content--incubator-freemarker--vocatan": 0,
        "#content--incubator-freemarker--robin850": 0,
        "#content--incubator-freemarker--ajbanck": 0,
        "#content--incubator-freemarker--ninjyni": 0,
        "#content--incubator-freemarker--chaquotay": 0,
        "#content--incubator-freemarker--fvanderwielen": 0,
        "#content--incubator-freemarker--jyjz2008": 0,
        "#content--incubator-freemarker--pitgrap": 0,
        "#content--incubator-freemarker--SimonLammer": 0,
        "#content--incubator-freemarker--pradeepmurugesan": 0,
        "#content--incubator-freemarker--pyxide": 0,
        "#content--incubator-freemarker--jacopoc": 0,
        "#content--incubator-freemarker--ratherblue": 0,
        "#content--incubator-freemarker--nanlei": 0,
        "#content--incubator-freemarker--mkleine": 0,
        "#content--incubator-freemarker--gamerson": 0,
        "#content--manifoldcf--rafaharo": 0.15384615384615385,
        "#content--manifoldcf--maoo": 0.05555555555555555,
        "#content--manifoldcf--": 0.018518518518518517,
        "#content--manifoldcf--kishorejangid": 0.01694915254237288,
        "#content--manifoldcf--kwrightapache": 0.014797136038186158,
        "#content--manifoldcf--sabe1": 0.014705882352941176,
        "#content--manifoldcf--schuch": 0,
        "#content--manifoldcf--OpenPj": 0,
        "#content--manifoldcf--danielshahaf": 0,
        "#content--manifoldcf--tteofili": 0,
        "#content--manifoldcf--gsingers": 0,
        "#content--manifoldcf--rmuir": 0,
        "#content--manifoldcf--markrmiller": 0,
        "#content--ofbiz--dixitdeepak": 0,
        "#content--ofbiz--pythys": 0,
        "#content--ofbiz--JacquesLeRoux": 0,
        "#content--ofbiz--nmalin": 0,
        "#content--ofbiz--mbrohl": 0,
        "#content--ofbiz--jacopoc": 0,
        "#content--ofbiz--shijh": 0,
        "#content--ofbiz--": 0,
        "#content--ofbiz--hansbak": 0,
        "#content--pdfbox--jahewson": 0.41863517060367456,
        "#content--pdfbox--jmaerki": 0.3611111111111111,
        "#content--pdfbox--lehmi": 0.35760667903525045,
        "#content--pdfbox--": 0.2814516129032258,
        "#content--pdfbox--jukka": 0.2542372881355932,
        "#content--pdfbox--THausherr": 0.15474234503360718,
        "#content--pdfbox--tballison": 0.125
    },
    "commiter_bug_number": {
        "#content--pdfbox--lehmi": 1101,
        "#content--pdfbox--THausherr": 885,
        "#content--pdfbox--": 553,
        "#content--pdfbox--jahewson": 546,
        "#content--pdfbox--jukka": 160,
        "#content--pdfbox--jmaerki": 72,
        "#content--manifoldcf--kwrightapache": 20,
        "#content--incubator-freemarker--ddekany": 10,
        "#content--manifoldcf--rafaharo": 6,
        "#content--manifoldcf--": 5,
        "#content--incubator-freemarker--woonsanko": 1,
        "#content--incubator-freemarker--szegedi": 1,
        "#content--manifoldcf--maoo": 1,
        "#content--manifoldcf--sabe1": 1,
        "#content--manifoldcf--kishorejangid": 1,
        "#content--pdfbox--tballison": 1
    },
    "number_inducing_commit": {
        "#content--incubator-freemarker--ddekany": 29,
        "#content--incubator-freemarker--woonsanko": 2,
        "#content--incubator-freemarker--szegedi": 1,
        "#content--manifoldcf--kwrightapache": 62,
        "#content--manifoldcf--": 4,
        "#content--manifoldcf--rafaharo": 4,
        "#content--manifoldcf--kishorejangid": 2,
        "#content--manifoldcf--maoo": 1,
        "#content--manifoldcf--sabe1": 1,
        "#content--pdfbox--THausherr": 1036,
        "#content--pdfbox--lehmi": 771,
        "#content--pdfbox--": 349,
        "#content--pdfbox--jahewson": 319,
        "#content--pdfbox--jukka": 60,
        "#content--pdfbox--jmaerki": 13,
        "#content--pdfbox--tballison": 1
    },
    "commiter_commit_number": {
        "#content--any23--": 910,
        "#content--any23--simonetripodi": 340,
        "#content--any23--lewismc": 221,
        "#content--any23--HansBrende": 165,
        "#content--any23--dependabot[bot]": 89,
        "#content--any23--ansell": 84,
        "#content--any23--michelemostarda": 70,
        "#content--any23--jgrzebyta": 49,
        "#content--any23--nisalanirmana": 10,
        "#content--any23--JulioCCBUcuenca": 8,
        "#content--any23--band": 6,
        "#content--any23--levkhomich": 4,
        "#content--any23--jdevelop": 3,
        "#content--any23--hboutemy": 2,
        "#content--any23--kamaci": 2,
        "#content--any23--scor": 2,
        "#content--any23--olamy": 2,
        "#content--any23--brnnnfx": 1,
        "#content--any23--NcIgor": 1,
        "#content--any23--tjroamer": 1,
        "#content--any23--JLLeitschuh": 1,
        "#content--any23--coheigea": 1,
        "#content--any23--panthony": 1,
        "#content--any23--davidcockbill": 1,
        "#content--any23--afs": 1,
        "#content--any23--larsgsvensson": 1,
        "#content--any23--frankier": 1,
        "#content--any23--The-Alchemist": 1,
        "#content--any23--jonathansantilli": 1,
        "#content--any23--Timpy": 1,
        "#content--incubator-freemarker--ddekany": 2164,
        "#content--incubator-freemarker--": 15,
        "#content--incubator-freemarker--szegedi": 14,
        "#content--incubator-freemarker--martin-g": 8,
        "#content--incubator-freemarker--woonsan": 7,
        "#content--incubator-freemarker--chrisrueger": 5,
        "#content--incubator-freemarker--pradeepmurugesan": 5,
        "#content--incubator-freemarker--woonsanko": 4,
        "#content--incubator-freemarker--ratherblue": 4,
        "#content--incubator-freemarker--quaff": 3,
        "#content--incubator-freemarker--pitgrap": 3,
        "#content--incubator-freemarker--powercomstar": 2,
        "#content--incubator-freemarker--ILyaCyclone": 2,
        "#content--incubator-freemarker--chaquotay": 2,
        "#content--incubator-freemarker--mkleine": 2,
        "#content--incubator-freemarker--theHacker": 1,
        "#content--incubator-freemarker--agriffis": 1,
        "#content--incubator-freemarker--TrackerSB": 1,
        "#content--incubator-freemarker--mbooth101": 1,
        "#content--incubator-freemarker--aschi": 1,
        "#content--incubator-freemarker--vocatan": 1,
        "#content--incubator-freemarker--robin850": 1,
        "#content--incubator-freemarker--ajbanck": 1,
        "#content--incubator-freemarker--ninjyni": 1,
        "#content--incubator-freemarker--fvanderwielen": 1,
        "#content--incubator-freemarker--jyjz2008": 1,
        "#content--incubator-freemarker--SimonLammer": 1,
        "#content--incubator-freemarker--pyxide": 1,
        "#content--incubator-freemarker--jacopoc": 1,
        "#content--incubator-freemarker--nanlei": 1,
        "#content--incubator-freemarker--gamerson": 1,
        "#content--manifoldcf--kwrightapache": 4190,
        "#content--manifoldcf--": 216,
        "#content--manifoldcf--kishorejangid": 118,
        "#content--manifoldcf--OpenPj": 101,
        "#content--manifoldcf--sabe1": 68,
        "#content--manifoldcf--schuch": 67,
        "#content--manifoldcf--rafaharo": 26,
        "#content--manifoldcf--maoo": 18,
        "#content--manifoldcf--rmuir": 7,
        "#content--manifoldcf--gsingers": 4,
        "#content--manifoldcf--danielshahaf": 1,
        "#content--manifoldcf--tteofili": 1,
        "#content--manifoldcf--markrmiller": 1,
        "#content--ofbiz--JacquesLeRoux": 64,
        "#content--ofbiz--pythys": 11,
        "#content--ofbiz--mbrohl": 6,
        "#content--ofbiz--nmalin": 5,
        "#content--ofbiz--jacopoc": 5,
        "#content--ofbiz--shijh": 2,
        "#content--ofbiz--dixitdeepak": 1,
        "#content--ofbiz--": 1,
        "#content--ofbiz--hansbak": 1,
        "#content--pdfbox--THausherr": 6695,
        "#content--pdfbox--lehmi": 2156,
        "#content--pdfbox--": 1240,
        "#content--pdfbox--jahewson": 762,
        "#content--pdfbox--jukka": 236,
        "#content--pdfbox--jmaerki": 36,
        "#content--pdfbox--tballison": 8
    },
    "team_developer_num": 90
}